mwxml/__init__.py
mwxml/about.py
mwxml/element_iterator.py
mwxml/errors.py
mwxml/mwxml.py
mwxml/files/__init__.py
mwxml/files/functions.py
mwxml/files/p7z.py
mwxml/files/tests/__init__.py
mwxml/files/tests/test_functions.py
mwxml/files/tests/test_p7z.py
mwxml/iteration/__init__.py
mwxml/iteration/dump.py
mwxml/iteration/log_item.py
mwxml/iteration/namespace.py
mwxml/iteration/page.py
mwxml/iteration/revision.py
mwxml/iteration/site_info.py
mwxml/iteration/slots.py
mwxml/iteration/user.py
mwxml/iteration/util.py
mwxml/iteration/tests/__init__.py
mwxml/iteration/tests/test_dump.py
mwxml/iteration/tests/test_log_item.py
mwxml/iteration/tests/test_namespace.py
mwxml/iteration/tests/test_page.py
mwxml/iteration/tests/test_revision.py
mwxml/iteration/tests/test_user.py
mwxml/map/__init__.py
mwxml/map/map.py
mwxml/map/processor.py
mwxml/map/tests/__init__.py
mwxml/map/tests/test_map.py
mwxml/new_map/__init__.py
mwxml/new_map/map.py
mwxml/tests/__init__.py
mwxml/tests/test_element_iterator.py
mwxml/utilities/__init__.py
mwxml/utilities/dump2revdocs.py
mwxml/utilities/inflate.py
mwxml/utilities/normalize.py
mwxml/utilities/validate.py
mwxml-0.3.5.dist-info/LICENSE
mwxml-0.3.5.dist-info/METADATA
mwxml-0.3.5.dist-info/WHEEL
mwxml-0.3.5.dist-info/entry_points.txt
mwxml-0.3.5.dist-info/top_level.txt
mwxml-0.3.5.dist-info/RECORD
