Metadata-Version: 2.1
Name: mwxml
Version: 0.3.5
Summary: A set of utilities for processing MediaWiki XML dump data.
Home-page: https://github.com/mediawiki-utilities/python-mwxml
Author: Aaron Halfaker
Author-email: aaron.halfaker@gmail.com
License: MIT
Platform: UNKNOWN
Classifier: Programming Language :: Python
Classifier: Programming Language :: Python :: 3
Classifier: Programming Language :: Python :: 3 :: Only
Classifier: Environment :: Other Environment
Classifier: Intended Audience :: Developers
Classifier: License :: OSI Approved :: MIT License
Classifier: Operating System :: OS Independent
Classifier: Topic :: Software Development :: Libraries :: Python Modules
Classifier: Topic :: Text Processing :: Linguistic
Classifier: Topic :: Text Processing :: General
Classifier: Topic :: Utilities
Classifier: Topic :: Scientific/Engineering
Requires-Dist: jsonschema (>=2.5.1)
Requires-Dist: mwcli (>=0.0.2)
Requires-Dist: mwtypes (>=0.4.0)
Requires-Dist: para (>=0.0.1)
